Metadata-Version: 2.4
Name: spex-tools
Version: 0.3.1059
Summary: Comprehensive spatial transcriptomics analysis library with advanced segmentation, clustering, and spatial analysis tools
Author: Aleksandr Prilipko
License-Expression: Apache-2.0
Project-URL: Homepage, https://genentech.github.io/spex-tools/
Project-URL: Repository, https://github.com/genentech/spex-tools
Project-URL: Documentation, https://genentech.github.io/spex-tools/
Requires-Python: >=3.11
License-File: LICENSE.md
Requires-Dist: aicsimageio==4.10.0
Requires-Dist: imagecodecs>=2020.5.30
Requires-Dist: fsspec>=2022.8.0
Requires-Dist: nd2>=0.2.0
Requires-Dist: mrc>=0.2.0
Requires-Dist: bfio==2.3.5
Requires-Dist: imageio-ffmpeg>=0.4
Requires-Dist: Pillow!=8.3.0,<9,>=8.2.0
Requires-Dist: ome-types==0.6.1
Requires-Dist: tifffile<2023.3.15,>=2022.8.12
Requires-Dist: numpy<1.26,>=1.25.2
Requires-Dist: pydantic==2.11.7
Requires-Dist: pydantic-core==2.33.2
Requires-Dist: pydantic-extra-types==2.10.5
Requires-Dist: typing_extensions>=4.7.1
Requires-Dist: bioformats-jar
Requires-Dist: jpype1
Requires-Dist: scikit-learn==1.3.2
Requires-Dist: scikit-image<0.20.0,>=0.19.3
Requires-Dist: scikit-misc>=0.1.5
Requires-Dist: dask==2021.11.1
Requires-Dist: keras==2.14.0
Requires-Dist: tensorflow==2.14.0
Requires-Dist: stardist==0.8.5
Requires-Dist: opencv-python==4.5.5.64
Requires-Dist: opencv-python-headless==4.5.5.64
Requires-Dist: csbdeep==0.7.4
Requires-Dist: protobuf<3.20.4,>=3.9.2
Requires-Dist: numexpr==2.8.4
Requires-Dist: packaging
Requires-Dist: cellpose==0.6.5
Requires-Dist: anndata==0.8.0
Requires-Dist: phenograph==1.5.7
Requires-Dist: scanpy==1.9.4
Requires-Dist: leidenalg==0.9.1
Requires-Dist: louvain==0.8.2
Requires-Dist: squidpy==1.2.2
Requires-Dist: scvi-tools[scanpy]==1.1.6.post2
Requires-Dist: jax==0.4.12
Requires-Dist: jaxlib==0.4.12
Requires-Dist: scipy<1.13,>=1.11.1
Requires-Dist: pegasuspy==1.10.2
Requires-Dist: treescope>=0.1.9
Requires-Dist: fastapi==0.115.14
Requires-Dist: pegasusio
Requires-Dist: pandas==2.2.0
Requires-Dist: decoupler==2.1.0
Requires-Dist: jaxtyping==0.3.2
Requires-Dist: flax==0.7.4
Requires-Dist: zarr==2.18.2
Requires-Dist: cython==3.1.2
Requires-Dist: requests==2.32.4
Requires-Dist: cmake==4.0.3
Requires-Dist: pyarrow==20.0.0
Requires-Dist: numcodecs==0.12.1
Provides-Extra: dev
Requires-Dist: pytest; extra == "dev"
Requires-Dist: ruff; extra == "dev"
Requires-Dist: black; extra == "dev"
Requires-Dist: pre-commit; extra == "dev"
Provides-Extra: docs
Requires-Dist: mkdocs-material; extra == "docs"
Requires-Dist: mkdocstrings[python]; extra == "docs"
Requires-Dist: mkdocs-jupyter; extra == "docs"
Dynamic: license-file
